microvault/__init__.py
microvault/algorithm/td3.py
microvault/components/replaybuffer.py
microvault/environment/__init__.py
microvault/environment/continuous.py
microvault/environment/generate.py
microvault/environment/robot.py
microvault/environment/utils/__init__.py
microvault/environment/utils/collision.py
microvault/environment/utils/map2d.py
microvault/environment/utils/world_generate.py
microvault/network/model.py
microvault/wrapper/wrapper.py
microvault-0.2.33.dist-info/LICENSE
microvault-0.2.33.dist-info/METADATA
microvault-0.2.33.dist-info/WHEEL
microvault-0.2.33.dist-info/RECORD
