Metadata-Version: 2.1
Name: microvault
Version: 0.2.33
Summary: Microvault - RL for Navigation
License: LICENSE
Author: Nicolasalan
Author-email: grottimeireles@gmail.com
Requires-Python: >=3.10,<4.0
Classifier: License :: Other/Proprietary License
Classifier: Programming Language :: Python :: 3
Classifier: Programming Language :: Python :: 3.10
Classifier: Programming Language :: Python :: 3.11
Classifier: Programming Language :: Python :: 3.12
Requires-Dist: accelerate (>=0.18.0,<0.19.0)
Requires-Dist: cython (>=3.0.8,<4.0.0)
Requires-Dist: fastrand (>=1.3.0,<2.0.0)
Requires-Dist: gymnasium (>=0.28.1,<0.29.0)
Requires-Dist: hydra-core (>=1.3.2,<2.0.0)
Requires-Dist: lightning (>=2.2.0,<3.0.0)
Requires-Dist: matplotlib (>=3.4.3,<4.0.0)
Requires-Dist: numba (>=0.59.1,<0.60.0)
Requires-Dist: numpy (>=1.24.2,<2.0.0)
Requires-Dist: omegaconf (>=2.3.0,<3.0.0)
Requires-Dist: openai (>=1.12.0,<2.0.0)
Requires-Dist: psutil (>=5.9.8,<6.0.0)
Requires-Dist: pymunk (>=6.6.0,<7.0.0)
Requires-Dist: pyyaml (>=6.0.1,<7.0.0)
Requires-Dist: scikit-image
Requires-Dist: scipy (>=1.12.0,<2.0.0)
Requires-Dist: torch (>=2.0.1,<3.0.0)
Requires-Dist: transformers (>=4.36.0,<5.0.0)
Requires-Dist: wget (>=3.2,<4.0)
Project-URL: bugs, https://github.com/microvault/microvault/issues
Project-URL: documentation, https://microvault.vercel.app
